coolCropper/__init__.py
coolCropper/crop.py
coolCropper-0.0.1.dist-info/LICENCE
coolCropper-0.0.1.dist-info/METADATA
coolCropper-0.0.1.dist-info/WHEEL
coolCropper-0.0.1.dist-info/top_level.txt
coolCropper-0.0.1.dist-info/RECORD
